4_counter.v
// 4_counter.v
module counter (
    input clk,
    input reset,
    output reg [3:0] count
);

// On positive clock or reset, either reset to 0 or increment
always @(posedge clk or posedge reset) begin
    if (reset)
        count <= 4'b0000;
    else
        count <= count + 1;
end

endmodule

tb_4_counter.v
// tb_4_counter.v
`timescale 1ns/1ps

module tb_counter;
    reg clk;
    reg reset;
    wire [3:0] count;

    // Instantiate DUT (Device Under Test)
    counter uut (
        .clk(clk),
        .reset(reset),
        .count(count)
    );

    // Generate clock with 10ns period
    initial clk = 0;
    always #5 clk = ~clk;

    // Test sequence
    initial begin
        $dumpfile("counter.vcd");
        $dumpvars(0, tb_counter);

        reset = 1; #10;
        reset = 0; // Release reset

        #100; // Let counter run
        $finish;
    end
endmodule

counter.vcd
$date
	Thu Aug 07 21:48:58 2025
$end
$version
	Icarus Verilog
$end
$timescale
	1ps
$end
$scope module tb_counter $end
$var wire 4 ! count [3:0] $end
$var reg 1 " clk $end
$var reg 1 # reset $end
$scope module uut $end
$var wire 1 " clk $end
$var wire 1 # reset $end
$var reg 4 $ count [3:0] $end
$upscope $end
$upscope $end
$enddefinitions $end
#0
$dumpvars
b0 $
1#
0"
b0 !
$end
#5000
1"
#10000
0"
0#
#15000
b1 !
b1 $
1"
#20000
0"
#25000
b10 !
b10 $
1"
#30000
0"
#35000
b11 !
b11 $
1"
#40000
0"
#45000
b100 !
b100 $
1"
#50000
0"
#55000
b101 !
b101 $
1"
#60000
0"
#65000
b110 !
b110 $
1"
#70000
0"
#75000
b111 !
b111 $
1"
#80000
0"
#85000
b1000 !
b1000 $
1"
#90000
0"
#95000
b1001 !
b1001 $
1"
#100000
0"
#105000
b1010 !
b1010 $
1"
